{
  "packageId": "app.gaveta_erp.twa",
  "host": "gaveta-erp.vercel.app",
  "name": "Gaveta",
  "launcherName": "Gaveta",
  "display": "standalone",
  "orientation": "default",
  "themeColor": "#1b7a43",
  "themeColorDark": "#1b7a43",
  "navigationColor": "#1b7a43",
  "navigationColorDark": "#1b7a43",
  "backgroundColor": "#ffffff",
  "startUrl": "/",
  "iconUrl": "https://gaveta-erp.vercel.app/icon-512.png",
  "maskableIconUrl": "https://gaveta-erp.vercel.app/icon-maskable-512.png",
  "webManifestUrl": "https://gaveta-erp.vercel.app/manifest.webmanifest",
  "fallbackType": "customtabs",
  "enableNotifications": false,
  "shortcuts": [],
  "features": {},
  "appVersionName": "1",
  "appVersionCode": 1,
  "minSdkVersion": 23,
  "isChromeOSOnly": false,
  "isMetaQuest": false,
  "fullScopeUrl": "https://gaveta-erp.vercel.app/",
  "additionalTrustedOrigins": [],
  "retainedBundles": []
}
